NestedLogger/__init__.py
NestedLogger/nested_logger.py
robotframework_nestedlogger-1.0.1.dist-info/LICENSE
robotframework_nestedlogger-1.0.1.dist-info/METADATA
robotframework_nestedlogger-1.0.1.dist-info/WHEEL
robotframework_nestedlogger-1.0.1.dist-info/top_level.txt
robotframework_nestedlogger-1.0.1.dist-info/RECORD
