Metadata-Version: 2.1
Name: robotframework-nestedlogger
Version: 1.0.1
Summary: A Robot Framework library for nested keyword logging in Python implementations
Home-page: https://github.com/yourusername/robotframework-NestedLogger
Author: Your Name
Author-email: your.email@example.com
License: Apache License 2.0
Project-URL: Bug Reports, https://github.com/yourusername/robotframework-NestedLogger/issues
Project-URL: Source, https://github.com/yourusername/robotframework-NestedLogger
Keywords: robotframework testing testautomation nested logging
Platform: any
Classifier: Development Status :: 4 - Beta
Classifier: Intended Audience :: Developers
Classifier: Topic :: Software Development :: Testing
Classifier: License :: OSI Approved :: Apache Software License
Classifier: Programming Language :: Python :: 3
Classifier: Programming Language :: Python :: 3.7
Classifier: Programming Language :: Python :: 3.8
Classifier: Programming Language :: Python :: 3.9
Classifier: Programming Language :: Python :: 3.10
Classifier: Programming Language :: Python :: 3.11
Classifier: Programming Language :: Python :: 3.12
Classifier: Framework :: Robot Framework
Classifier: Framework :: Robot Framework :: Library
Classifier: Framework :: Robot Framework :: Library
Requires-Python: >=3.10
License-File: LICENSE
Requires-Dist: robotframework>=7.3.0
Provides-Extra: dev
Requires-Dist: pytest>=7.0.0; extra == "dev"
Requires-Dist: pytest-cov>=3.0.0; extra == "dev"
